example_publish_pypi_medium/__init__.py
example_publish_pypi_medium/example/__init__.py
example_publish_pypi_medium/example/custom_sklearn.py
lyh_test-0.0.1.dist-info/METADATA
lyh_test-0.0.1.dist-info/WHEEL
lyh_test-0.0.1.dist-info/top_level.txt
lyh_test-0.0.1.dist-info/RECORD
