Metadata-Version: 2.1
Name: lyh_test
Version: 0.0.1
Author: Giorgos Myrianthous
Author-email: email@example.com
License: MIT
Requires-Dist: matplotlib
